odoo/addons/followers_mass_invoice_mailing/README.rst
odoo/addons/followers_mass_invoice_mailing/__init__.py
odoo/addons/followers_mass_invoice_mailing/__manifest__.py
odoo/addons/followers_mass_invoice_mailing/models/__init__.py
odoo/addons/followers_mass_invoice_mailing/models/account_invoice_send.py
odoo/addons/followers_mass_invoice_mailing/static/description/icon.png
odoo_addon_followers_mass_invoice_mailing-15.0.1.0.0.3.dist-info/METADATA
odoo_addon_followers_mass_invoice_mailing-15.0.1.0.0.3.dist-info/WHEEL
odoo_addon_followers_mass_invoice_mailing-15.0.1.0.0.3.dist-info/top_level.txt
odoo_addon_followers_mass_invoice_mailing-15.0.1.0.0.3.dist-info/RECORD
